{
  "title": "Newspaper Articles and Translations/MATERIAL PARA ENTREGAR: artículos de periódicos y traducciones",
  "outline": [
    {
      "level": "H1",
      "text": "LESSON: History Unfolded: Spanish Language Newspapers Coverage of the Holocaust",
      "page": 0
    },
    {
      "level": "H2",
      "text": "HANDOUT: Newspaper Articles and Translations",
      "page": 0
    },
    {
      "level": "H1",
      "text": "TÍTULO DE LA LECCIÓN: History Unfolded: cobertura del Holocausto en periódicos en español",
      "page": 0
    },
    {
      "level": "H2",
      "text": "MATERIAL PARA ENTREGAR: artículos de periódicos y traducciones",
      "page": 0
    },
    {
      "level": "H2",
      "text": "El Heraldo de Brownsville",
      "page": 0
    },
    {
      "level": "H3",
      "text": "El Heraldo de Brownsville was the Spanish-language of T he Brownsville Herald in Brownsville, Texas.",
      "page": 0
    },
    {
      "level": "H3",
      "text": "The newspaper published daily issues except on Saturdays. Brownsville is a city on the southern border of",
      "page": 0
    },
    {
      "level": "H3",
      "text": "the United States with Mexico.",
      "page": 0
    },
    {
      "level": "H3",
      "text": "El Heraldo de Brownsville era la versión en español de The Brownsville Herald de Brownsville, Texas. El",
      "page": 0
    },
    {
      "level": "H3",
      "text": "periódico publicaba ediciones diarias, excepto los sábados. Brownsville es una ciudad de la frontera sur",
      "page": 0
    },
    {
      "level": "H3",
      "text": "entre Estados Unidos y México.",
      "page": 0
    },
    {
      "level": "H2",
      "text": "El Mundo",
      "page": 0
    },
    {
      "level": "H3",
      "text": "El Mundo was a Spanish language newspaper in San Juan, Puerto Rico. Puerto Rico was in 1939 and still",
      "page": 0
    },
    {
      "level": "H3",
      "text": "is a territory of the United States as of 2020. El Mundo published daily issues. Puerto Rico and Cuba are",
      "page": 0
    },
    {
      "level": "H3",
      "text": "Carribean islands over 450 miles away from one another.",
      "page": 0
    },
    {
      "level": "H3",
      "text": "El Mundo era un periódico en español de San Juan de Puerto Rico. En 1939, Puerto Rico era territorio de",
      "page": 0
    },
    {
      "level": "H3",
      "text": "Estados Unidos y sigue siéndolo hasta la fecha. El Mundo publicaba ediciones diarias. Puerto Rico y",
      "page": 0
    },
    {
      "level": "H3",
      "text": "Cuba son islas del Caribe, separadas por una distancia de más de 720 kilómetros.",
      "page": 0
    },
    {
      "level": "H2",
      "text": "La Opinión",
      "page": 0
    },
    {
      "level": "H3",
      "text": "La Opinión is a Spanish-language newspaper in Los Angeles, California. In 1939, the newspaper printed",
      "page": 0
    },
    {
      "level": "H3",
      "text": "daily. Los Angeles is located in southern California about 130 miles north of the border with Mexico.",
      "page": 0
    },
    {
      "level": "H3",
      "text": "La Opinión es un periódico en español de Los Ángeles, California. En 1939, el periódico se imprimía",
      "page": 0
    },
    {
      "level": "H3",
      "text": "diariamente. Los Ángeles está situada en el sur de California, a unos 210 kilómetros al norte de la frontera",
      "page": 0
    },
    {
      "level": "H3",
      "text": "con México.",
      "page": 0
    },
    {
      "level": "H3",
      "text": "Newspaper Articles and Translations/artículos de periódicos y traducciones  | 1 of/de 13",
      "page": 0
    },
    {
      "level": "H3",
      "text": "Newspaper Articles and Translations/artículos de periódicos y traducciones  | 2 of/de 13",
      "page": 1
    },
    {
      "level": "H3",
      "text": "Newspaper Articles and Translations/artículos de periódicos y traducciones  | 3 of/de 13",
      "page": 2
    },
    {
      "level": "H3",
      "text": "El St. Louis Listo Para Abandonar La Bahía De La Habana",
      "page": 3
    },
    {
      "level": "H3",
      "text": "HABANA— El navío alemán “St. Louis” recibió combustible hoy en este puerto cubano y se hicieron los",
      "page": 3
    },
    {
      "level": "H3",
      "text": "preparativos correspondientes para que el navío se haga a la mar hoy mismo en viaje de regreso a",
      "page": 3
    },
    {
      "level": "H3",
      "text": "Alemania con los 917 refugiados Judíos a bordo.",
      "page": 3
    },
    {
      "level": "H3",
      "text": "Las autoridades no permitieron que desembarcaran en Cuba los semitas.",
      "page": 3
    },
    {
      "level": "H3",
      "text": "Los refugiados tenían esperanza de desembarcar en territorio cubano con el fin de viajar después a los",
      "page": 3
    },
    {
      "level": "H3",
      "text": "Estados Unidos de Norteamérica. Algunas mujeres prorrumpieron en llanto cuando se recibieron noticias",
      "page": 3
    },
    {
      "level": "H3",
      "text": "a bordo del “St. Louis” de que tendrían que regresar a Alemania, de donde huyeron hace tiempo.",
      "page": 3
    },
    {
      "level": "H3",
      "text": "El Capitán Gustave Schroeder, comandante del barco, teme que se registre una “ola de suicidios a bordo",
      "page": 3
    },
    {
      "level": "H3",
      "text": "del navío”.",
      "page": 3
    },
    {
      "level": "H3",
      "text": "El Presidente Cubano, Federico Laredo Bru, firmó un decreto ordenando al navío que abandone las",
      "page": 3
    },
    {
      "level": "H3",
      "text": "aguas territoriales de Cuba. Los Marinos Cubanos, miembros de la Marina del país se encontraban listos",
      "page": 3
    },
    {
      "level": "H3",
      "text": "para hacer cumplir el decreto presidencial.",
      "page": 3
    },
    {
      "level": "H3",
      "text": "No se permitió que desembarcaran los refugiados Judíos en vista de que no contaban sus pasaportes con",
      "page": 3
    },
    {
      "level": "H3",
      "text": "las visas consulares Cubanas y tampoco tienen los permisos correspondientes del Departamento del",
      "page": 3
    },
    {
      "level": "H3",
      "text": "Trabajo.",
      "page": 3
    },
    {
      "level": "H3",
      "text": "Newspaper Articles and Translations/artículos de periódicos y traducciones  | 4 of/de 13",
      "page": 3
    },
    {
      "level": "H3",
      "text": "The St. Louis Ready to Leave Havana Bay",
      "page": 4
    },
    {
      "level": "H3",
      "text": "HAVANA — The German ship “St. Louis” was refueled today in this Cuban port, and the corresponding",
      "page": 4
    },
    {
      "level": "H3",
      "text": "preparations were made for the ship to sail back to Germany today with 917 Jewish refugees on board.",
      "page": 4
    },
    {
      "level": "H3",
      "text": "The authorities did not allow the Semites to land in Cuba.",
      "page": 4
    },
    {
      "level": "H3",
      "text": "The refugees were hoping to land in Cuban territory in order to travel later to the United States of",
      "page": 4
    },
    {
      "level": "H3",
      "text": "America. Some women burst into tears when news came aboard the “St. Louis” that they would have to",
      "page": 4
    },
    {
      "level": "H3",
      "text": "return to Germany, from where they had fled some time ago.",
      "page": 4
    },
    {
      "level": "H3",
      "text": "Captain Gustave Schroeder, the ship's commander, fears a “wave of suicides aboard the ship.”",
      "page": 4
    },
    {
      "level": "H3",
      "text": "Cuban President Federico Laredo Bru signed a decree ordering the ship to leave Cuba's territorial",
      "page": 4
    },
    {
      "level": "H3",
      "text": "waters. The Cuban Marines, members of the country's Navy, were ready to enforce the presidential",
      "page": 4
    },
    {
      "level": "H3",
      "text": "decree.",
      "page": 4
    },
    {
      "level": "H3",
      "text": "The Jewish refugees were not allowed to go ashore because their passports did not have Cuban consular",
      "page": 4
    },
    {
      "level": "H3",
      "text": "visas and they did not have the corresponding permits from the Department of Labor.",
      "page": 4
    },
    {
      "level": "H3",
      "text": "Newspaper Articles and Translations/artículos de periódicos y traducciones  | 5 of/de 13",
      "page": 4
    },
    {
      "level": "H3",
      "text": "Link to article: http://dloc.com/CA03599022/00504/2x",
      "page": 5
    },
    {
      "level": "H3",
      "text": "Enlace al artículo: http://dloc.com/CA03599022/00504/2x",
      "page": 5
    },
    {
      "level": "H3",
      "text": "Newspaper Articles and Translations/artículos de periódicos y traducciones  | 6 of/de 13",
      "page": 5
    },
    {
      "level": "H3",
      "text": "Newspaper Articles and Translations/artículos de periódicos y traducciones  | 7 of/de 13",
      "page": 6
    },
    {
      "level": "H3",
      "text": "Cuba se niega a recibir novecientos refugiados judíos",
      "page": 7
    },
    {
      "level": "H3",
      "text": "Y anuncia que usará la fuerza para sacar de sus aguas al vapor en que viajan si no se aleja del puerto en",
      "page": 7
    },
    {
      "level": "H3",
      "text": "seguida",
      "page": 7
    },
    {
      "level": "H3",
      "text": "Por Laurence S. Haas",
      "page": 7
    },
    {
      "level": "H3",
      "text": "LA HABANA, junio 1. (P.U.) — El presidente de Cuba, doctor Federico Laredo Brú, emitió un decreto",
      "page": 7
    },
    {
      "level": "H3",
      "text": "prohibiendo el desembarco de los más de 900 refugiados judíos que hace cuatro días se encuentran a bordo del",
      "page": 7
    },
    {
      "level": "H3",
      "text": "vapor “St. Louis” en el puerto de La Habana, y ordenando que el barco salga inmediatamente de las aguas",
      "page": 7
    },
    {
      "level": "H3",
      "text": "cubanas. El decreto de Laredo Brú vino después de una conferencia con el presidente del Comité de",
      "page": 7
    },
    {
      "level": "H3",
      "text": "Inmigración de la Cámara, Pedro Mendieta, quien declaró a la prensa que el proyecto presentado en la Cámara",
      "page": 7
    },
    {
      "level": "H3",
      "text": "dispone la expulsión de todos los judíos que hayan llegado a Cuba desde el primero de noviembre a esta parte.",
      "page": 7
    },
    {
      "level": "H3",
      "text": "Se calcula que desde entonces han llegado como 4,000 judíos de los que se dice que han entrado ilegalmente.",
      "page": 7
    },
    {
      "level": "H3",
      "text": "El Secretario del Tesoro dio instrucciones para que se investigue la cuestión del “St. Louis” y se determine",
      "page": 7
    },
    {
      "level": "H3",
      "text": "responsabilidades en cuanto a la transportación de judíos a Cuba violando las regulaciones de inmigración.",
      "page": 7
    },
    {
      "level": "H3",
      "text": "Mientras tanto el vapor se halla surto en medio del puerto vigilado por una patrulla de policía portuaria que no",
      "page": 7
    },
    {
      "level": "H3",
      "text": "permite que persona alguna suba a bordo y que evita que las demás embarcaciones se acerquen al barco lleno",
      "page": 7
    },
    {
      "level": "H3",
      "text": "de judíos. Una lancha de la Policía da vueltas alrededor de la nave cuyas barandillas están atestadas de",
      "page": 7
    },
    {
      "level": "H3",
      "text": "refugiados que miran anhelantemente hacia tierra.",
      "page": 7
    },
    {
      "level": "H3",
      "text": "El abogado de la compañía naviera dijo que el “St. Louis” no saldrá del puerto mientras no se decida el asunto",
      "page": 7
    },
    {
      "level": "H3",
      "text": "en las cortes de justicia. “Vamos a luchar”, dijo. Se informa que el barco está deseoso de desembarcar los",
      "page": 7
    },
    {
      "level": "H3",
      "text": "refugiados debido a los gastos que ocasionan 2,800 comidas diarias. Pero se rumora que los pasajeros tuvieron",
      "page": 7
    },
    {
      "level": "H3",
      "text": "que pagar de antemano pasaje de ida y vuelta desde Hamburgo como precaución ante la posibilidad de que",
      "page": 7
    },
    {
      "level": "H3",
      "text": "tuvieran que regresar a Alemania.",
      "page": 7
    },
    {
      "level": "H3",
      "text": "Aunque los refugiados trajeron pasaportes visados por las autoridades consulares cubanas en Alemania, el",
      "page": 7
    },
    {
      "level": "H3",
      "text": "Gobierno cubano dice que estas visas fueron extendidas en violación al reciente reglamento de inmigración",
      "page": 7
    },
    {
      "level": "H3",
      "text": "que prohíbe la entrada de más judíos a Cuba. En los cuatro días que la nave ha estado en el puerto ha habido",
      "page": 7
    },
    {
      "level": "H3",
      "text": "dos tentativas de suicidio. Pero en general los refugiados no dan la impresión de estar desalentados.",
      "page": 7
    },
    {
      "level": "H3",
      "text": "Entrevistados desde una lancha la mayoría demuestra optimismo. Algunos sin embargo aparecen ansiosos con",
      "page": 7
    },
    {
      "level": "H3",
      "text": "la prolongada espera.",
      "page": 7
    },
    {
      "level": "H3",
      "text": "El decreto que finalmente destruye todas las esperanzas de desembarcar dispone el “uso de la fuerza pública”",
      "page": 7
    },
    {
      "level": "H3",
      "text": "para sacar al “St. Louis” de las aguas cubanas en caso de que la Línea Hamburg-American no cumpla con la",
      "page": 7
    },
    {
      "level": "H3",
      "text": "orden de salir. El decreto también especifica que todos los pasajeros deben permanecer a bordo porque “su",
      "page": 7
    },
    {
      "level": "H3",
      "text": "desembarco no ha sido autorizado” y provee el arresto de cualquier miembro de la tripulación o pasajero que",
      "page": 7
    },
    {
      "level": "H3",
      "text": "desembarque ilegalmente escapándose de la nave.",
      "page": 7
    },
    {
      "level": "H3",
      "text": "Newspaper Articles and Translations/artículos de periódicos y traducciones  | 8 of/de 13",
      "page": 7
    },
    {
      "level": "H3",
      "text": "Cuba Refuses to Receive Nine Hundred Jewish Refugees",
      "page": 8
    },
    {
      "level": "H3",
      "text": "And it announces that it will resort to force to remove the steamer they are traveling in from Cuban waters",
      "page": 8
    },
    {
      "level": "H3",
      "text": "if it does not leave the port at once",
      "page": 8
    },
    {
      "level": "H3",
      "text": "By Laurence S. Haas",
      "page": 8
    },
    {
      "level": "H3",
      "text": "HAVANA, June 1. (P.U.) — The president of Cuba, Dr. Federico Laredo Bru, issued a decree prohibiting",
      "page": 8
    },
    {
      "level": "H3",
      "text": "the landing of more than 900 Jewish refugees who have been on board the steamer “St. Louis” in the port",
      "page": 8
    },
    {
      "level": "H3",
      "text": "of Havana for four days, and ordering the ship to leave Cuban waters immediately. Laredo Bru’s decree",
      "page": 8
    },
    {
      "level": "H3",
      "text": "came after a conference with the president of the House Immigration Committee, Pedro Mendieta, who",
      "page": 8
    },
    {
      "level": "H3",
      "text": "told the press that the bill presented in the House provides for the expulsion of all Jews who arrived in",
      "page": 8
    },
    {
      "level": "H3",
      "text": "Cuba since November 1st. It is estimated that since then, about 4,000 Jews have arrived and are said to",
      "page": 8
    },
    {
      "level": "H3",
      "text": "have entered illegally.",
      "page": 8
    },
    {
      "level": "H3",
      "text": "The Secretary of the Treasury instructed that the “St. Louis” issue be investigated and that responsibility",
      "page": 8
    },
    {
      "level": "H3",
      "text": "be determined for the transportation of Jews to Cuba in violation of immigration regulations. Meanwhile,",
      "page": 8
    },
    {
      "level": "H3",
      "text": "the steamer is anchored in the middle of the harbor, guarded by a port police patrol that does not allow",
      "page": 8
    },
    {
      "level": "H3",
      "text": "anyone on board and prevents other boats from approaching the ship full of Jews. A police boat circles the",
      "page": 8
    },
    {
      "level": "H3",
      "text": "ship whose railings are crowded with refugees looking longingly toward land.",
      "page": 8
    },
    {
      "level": "H3",
      "text": "The shipping company's lawyer said that the “St. Louis” will not leave the port until the matter is decided",
      "page": 8
    },
    {
      "level": "H3",
      "text": "in the courts of law. “We are going to fight,” he said. The ship is reportedly eager to disembark the",
      "page": 8
    },
    {
      "level": "H3",
      "text": "refugees due to the expense of 2,800 meals per day. But it is rumored that the passengers had to pay return",
      "page": 8
    },
    {
      "level": "H3",
      "text": "fares from Hamburg in advance as a precaution against having to return to Germany.",
      "page": 8
    },
    {
      "level": "H3",
      "text": "Although the refugees brought passports that had been endorsed by Cuban consular authorities in",
      "page": 8
    },
    {
      "level": "H3",
      "text": "Germany, the Cuban Government says that those visas were extended in violation of recent immigration",
      "page": 8
    },
    {
      "level": "H3",
      "text": "regulations that prohibit the entry of more Jews into Cuba. In the four days that the ship has been in port,",
      "page": 8
    },
    {
      "level": "H3",
      "text": "there have been two suicide attempts. But in general, the refugees do not give the impression of being",
      "page": 8
    },
    {
      "level": "H3",
      "text": "discouraged. Interviewed from a boat, most show optimism. Some, however, look anxious about the long",
      "page": 8
    },
    {
      "level": "H3",
      "text": "wait.",
      "page": 8
    },
    {
      "level": "H3",
      "text": "The decree that finally destroys all hope of landing provides for the “use of public force” to remove the",
      "page": 8
    },
    {
      "level": "H3",
      "text": "“St. Louis” from Cuban waters in case the Hamburg-American Line does not comply with the order to",
      "page": 8
    },
    {
      "level": "H3",
      "text": "leave. The decree also specifies that all passengers must remain on board because “their disembarkation",
      "page": 8
    },
    {
      "level": "H3",
      "text": "has not been authorized” and provides for the arrest of any crew member or passenger who illegally",
      "page": 8
    },
    {
      "level": "H3",
      "text": "disembarks by escaping from the ship.",
      "page": 8
    },
    {
      "level": "H3",
      "text": "Newspaper Articles and Translations/artículos de periódicos y traducciones  | 9 of/de 13",
      "page": 8
    },
    {
      "level": "H3",
      "text": "Link to article:",
      "page": 9
    },
    {
      "level": "H3",
      "text": "https://news.google.com/newspapers?nid=A8NefVh_EAoC&dat=19390602&printsec=frontpage&hl=en",
      "page": 9
    },
    {
      "level": "H3",
      "text": "Enlace al artículo:",
      "page": 9
    },
    {
      "level": "H3",
      "text": "Newspaper Articles and Translations/artículos de periódicos y traducciones  | 10 of/de 13",
      "page": 9
    },
    {
      "level": "H3",
      "text": "Newspaper Articles and Translations/artículos de periódicos y traducciones  | 11 of/de 13",
      "page": 10
    },
    {
      "level": "H3",
      "text": "EXPULSARÁN DE CUBA A TODOS LOS ISRAELITAS",
      "page": 11
    },
    {
      "level": "H3",
      "text": "Han entrado ilegalmente más de cuatro mil judíos",
      "page": 11
    },
    {
      "level": "H3",
      "text": "HABANA, Cuba, Junio 1ro. — (UP) — Una expulsión en masa de los judíos residentes en Cuba, se",
      "page": 11
    },
    {
      "level": "H3",
      "text": "perfilaba hoy, después de que el Presidente Federico Laredo Bru negó permiso para que desembarcaron",
      "page": 11
    },
    {
      "level": "H3",
      "text": "aquí más de 900 judíos que llegaron procedente de Alemania a bordo del barco San Luis.",
      "page": 11
    },
    {
      "level": "H3",
      "text": "El Presidente Laredo Bru expidió una orden de que el San Luis salga inmediatamente de aguas cubanas",
      "page": 11
    },
    {
      "level": "H3",
      "text": "con todos sus pasajeros. Este decreto se dio a conocer a Luis Clasing, agente de la compañía naviera",
      "page": 11
    },
    {
      "level": "H3",
      "text": "Hamburg-American, después de que Pedro Mendieta, presidente del Comité de Inmigración de la Cámara",
      "page": 11
    },
    {
      "level": "H3",
      "text": "de Diputados, había conferenciado con el Presidente Bru en el Palacio.",
      "page": 11
    },
    {
      "level": "H3",
      "text": "Mendieta declaró a los reporteros que se proponía hablar con el Presidente respecto a un proyecto de ley",
      "page": 11
    },
    {
      "level": "H3",
      "text": "que ser presentado a la Cámara de Diputados, proponiendo la expulsión de todos los judíos que han",
      "page": 11
    },
    {
      "level": "H3",
      "text": "llegado a Cuba desde el 1ro. de noviembre pasado. Estos judíos que se calculan en un total de … 4,000",
      "page": 11
    },
    {
      "level": "H3",
      "text": "entraron ilegalmente al país según declara Mendieta.",
      "page": 11
    },
    {
      "level": "H3",
      "text": "El decreto presidencial, que mató toda esperanza de los refugiados judíos de desembarcar aquí, establece",
      "page": 11
    },
    {
      "level": "H3",
      "text": "el uso de las “fuerzas públicas” para obligar al San Luis a [SK1] salir de las aguas territoriales cubanas en",
      "page": 11
    },
    {
      "level": "H3",
      "text": "caso de que la Hamburg-American Lines se niegue a obedecer la orden. Todos los pasajeros deben",
      "page": 11
    },
    {
      "level": "H3",
      "text": "permanecer a bordo “porque su desembarque no ha sido autorizado”, y cualquier miembro de la",
      "page": 11
    },
    {
      "level": "H3",
      "text": "tripulación que sea sorprendido en tierra será arrestado.",
      "page": 11
    },
    {
      "level": "H3",
      "text": "El Ministro del Tesoro recibió instrucciones de investigar el caso, y deslindar responsabilidades por la",
      "page": 11
    },
    {
      "level": "H3",
      "text": "traída de los refugiados judíos en violación de las leyes de migración de Cuba.",
      "page": 11
    },
    {
      "level": "H3",
      "text": "Se sabe que todos los refugiados traen visas consulares expedidas por el Consulado de Cuba en Alemania,",
      "page": 11
    },
    {
      "level": "H3",
      "text": "pero el gobierno alega que esas visas fueron dadas en contravención de las recientes leyes de migración",
      "page": 11
    },
    {
      "level": "H3",
      "text": "que prohíben el desembarque de más refugiados judíos en Cuba.",
      "page": 11
    },
    {
      "level": "H3",
      "text": "El San Luis continúa anclado en la bahía, mientras que la policía cuida que no desembarque ninguno de",
      "page": 11
    },
    {
      "level": "H3",
      "text": "sus tripulantes.",
      "page": 11
    },
    {
      "level": "H3",
      "text": "Newspaper Articles and Translations/artículos de periódicos y traducciones  | 12 of/de 13",
      "page": 11
    },
    {
      "level": "H3",
      "text": "ALL ISRAELITES WILL BE EXPELLED FROM CUBA",
      "page": 12
    },
    {
      "level": "H3",
      "text": "More than four thousand Jews have entered illegally",
      "page": 12
    },
    {
      "level": "H3",
      "text": "Havana, Cuba, June 1 (UP) - A mass expulsion of Jews residing in Cuba was outlined today, after",
      "page": 12
    },
    {
      "level": "H3",
      "text": "President Frederico Laredo Bru denied permission to disembark here more than 900 Jews who arrived",
      "page": 12
    },
    {
      "level": "H3",
      "text": "from Germany aboard the San Luis ship.",
      "page": 12
    },
    {
      "level": "H3",
      "text": "President Laredo Bru issued an order that the San Luis leave immediately Cuban waters with all its",
      "page": 12
    },
    {
      "level": "H3",
      "text": "passengers. This decree was made known to Luis Clasing, agent of the company in Hamburg-American",
      "page": 12
    },
    {
      "level": "H3",
      "text": "after Pedro Mendieta, president of the immigration committee of the Chamber of Deputies, had conferred",
      "page": 12
    },
    {
      "level": "H3",
      "text": "with President Bru in the Palace.",
      "page": 12
    },
    {
      "level": "H3",
      "text": "Mendieta told reporters that he intended to speak with the President regarding a bill to be presented to the",
      "page": 12
    },
    {
      "level": "H3",
      "text": "Chamber of Deputies, proposing the expulsion of all Jews who have arrived in Cuba since November 1.",
      "page": 12
    },
    {
      "level": "H3",
      "text": "These Jews, which are estimated at a total of ... 4,000, entered the country illegally according to",
      "page": 12
    },
    {
      "level": "H3",
      "text": "Mendieta.",
      "page": 12
    },
    {
      "level": "H3",
      "text": "The Presidential decree, which killed all hope of Jewish refugees to disembark here, established the use of",
      "page": 12
    },
    {
      "level": "H3",
      "text": "\"public forces\" to force San Luisa out of Cuban territorial waters in case the Hamburg-American Lines",
      "page": 12
    },
    {
      "level": "H3",
      "text": "refuses to obey the order. All passengers must remain on board \"because their disembarkation has not",
      "page": 12
    },
    {
      "level": "H3",
      "text": "been authorized,\" and any crew member caught on the ground will be arrested.",
      "page": 12
    },
    {
      "level": "H3",
      "text": "The Treasury Minister was instructed to investigate the case and disclaim responsibilities for bringing",
      "page": 12
    },
    {
      "level": "H3",
      "text": "Jewish refugees in violation of Cuba's immigration laws.",
      "page": 12
    },
    {
      "level": "H3",
      "text": "It is known that all refugees bring consular visas issued by the Consulate of Cuba in Germany, but the",
      "page": 12
    },
    {
      "level": "H3",
      "text": "government alleges that those visas were given in contravention of recent migration laws that prohibit the",
      "page": 12
    },
    {
      "level": "H3",
      "text": "landing of more Jewish refugees in Cuba.",
      "page": 12
    },
    {
      "level": "H3",
      "text": "The San Luis continues anchored in the bay while the police take care not to disembark any of its crew.",
      "page": 12
    },
    {
      "level": "H3",
      "text": "Newspaper Articles and Translations/artículos de periódicos y traducciones  | 13 of/de 13",
      "page": 12
    }
  ]
}